probnet/__init__.py
probnet/helpers/__init__.py
probnet/helpers/data_handler.py
probnet/helpers/distance.py
probnet/helpers/kernel.py
probnet/helpers/metrics.py
probnet/helpers/scaler.py
probnet/helpers/validator.py
probnet/models/__init__.py
probnet/models/base_net.py
probnet/models/grnn.py
probnet/models/pnn.py
probnet-0.2.0.dist-info/licenses/LICENSE
probnet-0.2.0.dist-info/METADATA
probnet-0.2.0.dist-info/WHEEL
probnet-0.2.0.dist-info/top_level.txt
probnet-0.2.0.dist-info/RECORD
